anifetch_rs-0.1.3.dist-info/METADATA
anifetch_rs-0.1.3.dist-info/WHEEL
anifetch_rs-0.1.3.dist-info/entry_points.txt
anifetch_rs-0.1.3.dist-info/licenses/LICENSE
anifetch_rs/__init__.py
anifetch_rs/anifetch_rs.cpython-311-aarch64-linux-gnu.so
anifetch_rs-0.1.3.dist-info/RECORD
