Metadata-Version: 2.4
Name: anifetch-rs
Version: 0.1.3
Classifier: Programming Language :: Rust
Classifier: Programming Language :: Python :: Implementation :: CPython
License-File: LICENSE
Summary: Terminal video fetch tool
Requires-Python: >=3.7
